mcp_modules_pkg/__init__.py
mcp_modules_pkg/credentials/__init__.py
mcp_modules_pkg/db_connector/__init__.py
mcp_modules_pkg/db_connector/base.py
mcp_modules_pkg/db_connector/clickhouse.py
mcp_modules_pkg/db_connector/connection.py
mcp_modules_pkg/db_connector/database.py
mcp_modules_pkg/db_connector/impala.py
mcp_modules_pkg/db_connector/milvus.py
mcp_modules_pkg/db_connector/mongodb.py
mcp_modules_pkg/db_connector/mysql.py
mcp_modules_pkg/db_connector/postgre.py
mcp_modules_pkg/db_connector/starrocks.py
mcp_modules_pkg/mcp_modules/__init__.py
mcp_modules_pkg/mcp_modules/base_invoker.py
mcp_modules_pkg/mcp_modules/mcp_logger.py
yepark_mcp_modules_pkg-0.1.2.dist-info/METADATA
yepark_mcp_modules_pkg-0.1.2.dist-info/WHEEL
yepark_mcp_modules_pkg-0.1.2.dist-info/top_level.txt
yepark_mcp_modules_pkg-0.1.2.dist-info/RECORD
