Metadata-Version: 2.4
Name: yepark-mcp-modules-pkg
Version: 0.1.2
Summary: 통합된 DB connector, gspread 인증 파일, MCP 모듈(base invoker, mcp loggers) 패키지
Author-email: yepark <yepark@bitmango.com>
License: MIT
Project-URL: Homepage, https://github.com/yourusername/mcp-modules-pkg
Project-URL: Repository, https://github.com/yourusername/mcp-modules-pkg
Project-URL: Issues, https://github.com/yourusername/mcp-modules-pkg/issues
Keywords: database,credentials,mcp
Classifier: Programming Language :: Python :: 3
Classifier: License :: OSI Approved :: MIT License
Classifier: Operating System :: OS Independent
Requires-Python: >=3.11
Requires-Dist: llm
Requires-Dist: llm-gemini
Requires-Dist: gspread
Requires-Dist: pandas
Requires-Dist: pymongo
Requires-Dist: psycopg2-binary
Requires-Dist: sqlalchemy
Requires-Dist: cryptography
